LICENSE
MANIFEST.in
README.md
setup.py
src/textpruner/__init__.py
src/textpruner/configurations.py
src/textpruner/model_map.py
src/textpruner/utils.py
src/textpruner.egg-info/PKG-INFO
src/textpruner.egg-info/SOURCES.txt
src/textpruner.egg-info/dependency_links.txt
src/textpruner.egg-info/entry_points.txt
src/textpruner.egg-info/requires.txt
src/textpruner.egg-info/top_level.txt
src/textpruner/commands/__init__.py
src/textpruner/commands/functions.py
src/textpruner/commands/textpruner_cli.py
src/textpruner/commands/utils.py
src/textpruner/model_utils/__init__.py
src/textpruner/model_utils/albert.py
src/textpruner/model_utils/bart.py
src/textpruner/model_utils/bert.py
src/textpruner/model_utils/electra.py
src/textpruner/model_utils/model_structure.py
src/textpruner/model_utils/mt5.py
src/textpruner/model_utils/roberta.py
src/textpruner/model_utils/t5.py
src/textpruner/model_utils/utils.py
src/textpruner/model_utils/xlm.py
src/textpruner/model_utils/xlm_roberta.py
src/textpruner/pruners/__init__.py
src/textpruner/pruners/pipeline_pruner.py
src/textpruner/pruners/transformer_pruner.py
src/textpruner/pruners/utils.py
src/textpruner/pruners/vocabulary_pruner.py
src/textpruner/tokenizer_utils/__init__.py
src/textpruner/tokenizer_utils/mt5_sp_tokenizer.py
src/textpruner/tokenizer_utils/roberta_gpt2_tokenizer.py
src/textpruner/tokenizer_utils/sp_tokenizer.py
src/textpruner/tokenizer_utils/subword_tokenizer.py
src/textpruner/tokenizer_utils/t5_sp_tokenizer.py
src/textpruner/tokenizer_utils/utils.py
src/textpruner/tokenizer_utils/xlm_tokenizer.py
src/textpruner/tokenizer_utils/xlmr_sp_tokenizer.py